rockset/__init__.py
rockset/api/__init__.py
rockset/api/aliases_api.py
rockset/api/api_keys_api.py
rockset/api/collections_api.py
rockset/api/custom_roles_api.py
rockset/api/documents_api.py
rockset/api/integrations_api.py
rockset/api/organizations_api.py
rockset/api/queries_api.py
rockset/api/query_lambdas_api.py
rockset/api/users_api.py
rockset/api/views_api.py
rockset/api/virtual_instances_api.py
rockset/api/workspaces_api.py
rockset/api_client.py
rockset/apis/__init__.py
rockset/configuration.py
rockset/document.py
rockset/exceptions.py
rockset/model/__init__.py
rockset/model/add_documents_request.py
rockset/model/add_documents_response.py
rockset/model/alias.py
rockset/model/api_key.py
rockset/model/async_query_options.py
rockset/model/aws_access_key.py
rockset/model/aws_role.py
rockset/model/azure_blob_storage_collection_creation_request.py
rockset/model/azure_blob_storage_integration.py
rockset/model/azure_blob_storage_integration_creation_request.py
rockset/model/azure_blob_storage_source_wrapper.py
rockset/model/azure_event_hubs_collection_creation_request.py
rockset/model/azure_event_hubs_integration.py
rockset/model/azure_event_hubs_integration_creation_request.py
rockset/model/azure_event_hubs_source_wrapper.py
rockset/model/azure_service_bus_collection_creation_request.py
rockset/model/azure_service_bus_integration.py
rockset/model/azure_service_bus_source_wrapper.py
rockset/model/cancel_query_response.py
rockset/model/cluster.py
rockset/model/collection.py
rockset/model/collection_stats.py
rockset/model/create_alias_request.py
rockset/model/create_alias_response.py
rockset/model/create_api_key_request.py
rockset/model/create_api_key_response.py
rockset/model/create_collection_request.py
rockset/model/create_collection_response.py
rockset/model/create_integration_request.py
rockset/model/create_integration_response.py
rockset/model/create_query_lambda_request.py
rockset/model/create_query_lambda_tag_request.py
rockset/model/create_role_request.py
rockset_v2_alpha-0.1.13.dist-info/WHEEL
rockset_v2_alpha-0.1.13.dist-info/METADATA
rockset_v2_alpha-0.1.13.dist-info/RECORD
